cs50/__init__.py
cs50/cs50.py
cs50/flask.py
cs50/sql.py
cs50-9.4.0.dist-info/LICENSE
cs50-9.4.0.dist-info/METADATA
cs50-9.4.0.dist-info/WHEEL
cs50-9.4.0.dist-info/top_level.txt
cs50-9.4.0.dist-info/RECORD
