Metadata-Version: 2.1
Name: cs50
Version: 9.4.0
Summary: CS50 library for Python
Home-page: https://github.com/cs50/python-cs50
Author: CS50
Author-email: sysadmins@cs50.harvard.edu
License: GPLv3
Keywords: cs50
Classifier: Intended Audience :: Developers
Classifier: Programming Language :: Python
Classifier: Programming Language :: Python :: 3
Classifier: Topic :: Software Development :: Libraries :: Python Modules
License-File: LICENSE
